nb_aiohttp/__init__.py
nb_aiohttp/nb_aiohttp_m.py
nb_aiohttp/nb_synchttp.py
nb_aiohttp/nbhttp_instance.py
nb_aiohttp-1.4.dist-info/METADATA
nb_aiohttp-1.4.dist-info/WHEEL
nb_aiohttp-1.4.dist-info/top_level.txt
nb_aiohttp-1.4.dist-info/RECORD
