Metadata-Version: 2.4
Name: nb_aiohttp
Version: 1.4
Summary: 更好用的 aiohttp 客户端，支持同步和异步使用。 性能碾压 httpx 和 requests 400%
Author-email: ydf0509 <ydf0509@xxx.com>
License: MIT
Project-URL: Homepage, https://github.com/ydf0509/nb_aiohttp
Project-URL: Repository, https://github.com/ydf0509/nb_aiohttp
Project-URL: Issues, https://github.com/ydf0509/nb_aiohttp/issues
Keywords: asyncio,aiohttp,httpx
Classifier: Development Status :: 3 - Alpha
Classifier: Intended Audience :: Developers
Classifier: License :: OSI Approved :: MIT License
Classifier: Programming Language :: Python :: 3
Classifier: Programming Language :: Python :: 3.7
Classifier: Programming Language :: Python :: 3.8
Classifier: Programming Language :: Python :: 3.9
Classifier: Programming Language :: Python :: 3.10
Classifier: Programming Language :: Python :: 3.11
Classifier: Programming Language :: Python :: 3.12
Classifier: Programming Language :: Python :: 3.13
Classifier: Programming Language :: Python :: 3.14
Requires-Python: >=3.7
Requires-Dist: typing_extensions>=3.7; python_version < "3.8"
Requires-Dist: aiohttp
Requires-Dist: nb_log
Provides-Extra: test
Requires-Dist: pytest>=6.0; extra == "test"
Requires-Dist: pytest-asyncio>=0.14; extra == "test"
Provides-Extra: dev
Requires-Dist: black>=21.0; extra == "dev"
Requires-Dist: flake8>=3.8; extra == "dev"
Requires-Dist: mypy>=0.812; extra == "dev"
